<?xml version="1.0" encoding="utf-8" ?>
<dwsync>
<file name="2dbarcodes.php" server="rsvpmaker.com/public_html/" local="129485909399102877" remote="129498635210000000" />
<file name="barcodes.php" server="rsvpmaker.com/public_html/" local="129485909400252943" remote="129498635220000000" />
<file name="CHANGELOG.TXT" server="rsvpmaker.com/public_html/" local="129485909400872978" remote="129498635270000000" />
<file name="htmlcolors.php" server="rsvpmaker.com/public_html/" local="129485909401423010" remote="129498637890000000" />
<file name="LICENSE.TXT" server="rsvpmaker.com/public_html/" local="129485909402143051" remote="129498638130000000" />
<file name="pdf417.php" server="rsvpmaker.com/public_html/" local="129485909402733085" remote="129498638150000000" />
<file name="qrcode.php" server="rsvpmaker.com/public_html/" local="129485909403713141" remote="129498638160000000" />
<file name="README.TXT" server="rsvpmaker.com/public_html/" local="129485909404063161" remote="129498638170000000" />
<file name="tcpdf.crt" server="rsvpmaker.com/public_html/" local="129485909404363178" remote="129498638170000000" />
<file name="tcpdf.fdf" server="rsvpmaker.com/public_html/" local="129485909404653195" remote="129498638170000000" />
<file name="tcpdf.p12" server="rsvpmaker.com/public_html/" local="129485909405093220" remote="129498638180000000" />
<file name="tcpdf.php" server="rsvpmaker.com/public_html/" local="129485909412023616" remote="129498638280000000" />
<file name="unicode_data.php" server="rsvpmaker.com/public_html/" local="129485909421604164" remote="129498638310000000" />
</dwsync>